[
  {
    "package": "rave",
    "url": "https://github.com/beauchamplab/rave",
    "via": ["ravebuiltins"],
    "from": "ravebuiltins"
  },
  {
    "package": "ravetools",
    "url": "https://github.com/dipterix/ravetools",
    "via": ["threeBrain"],
    "from": "threeBrain"
  },
  {
    "package": "rpymat",
    "url": "https://github.com/dipterix/rpymat",
    "via": ["rnwb"],
    "from": "rnwb"
  },
  {
    "package": "rutabaga",
    "url": "https://github.com/dipterix/rutabaga",
    "via": ["ravebuiltins"],
    "from": "ravebuiltins"
  }
]
